{
    "points": {
        "ホームポジション": {
            "x": 133,
            "y": 57,
            "angle": -69.15,
            "name": "ホームポジション"
        },
        "会話位置": {
            "x": 31,
            "y": 61,
            "angle": 111.43,
            "name": "会話位置3"
        },
        "アームと会話位置": {
            "x": 110,
            "y": 35,
            "angle": -125.33,
            "name": "アームと会話"
        },
        "把持台": {
            "x": 84,
            "y": 67,
            "angle": 113.02,
            "name": "把持台3"
        }
    },
    "routes": {
        "ゴール回避": {
            "route_position": [
                { "x": 524, "y": 430 },
                { "x": 480, "y": 435 },
                { "x": 474, "y": 466 },
                { "x": 493, "y": 491 },
                { "x": 521, "y": 496 },
                { "x": 572, "y": 498 }
            ],
            "route_angle": "-7.1"
        },
        "牽引ルート": {
            "route_position": [
                { "x": 639, "y": 515 },
                { "x": 703, "y": 522 }
            ],
            "route_angle": "-104.5"
        }
    }
}
